coded/__init__.py
coded/x.py
coded-1.132.dist-info/METADATA
coded-1.132.dist-info/WHEEL
coded-1.132.dist-info/RECORD
